{"conditionname1_input": "Condition", "colors_config": {"AAColorProc ApproxColor_Small - Correct": [202, 145, 243], "Errors": [12, 160, 191], "Add Cue": [57, 90, 64], "Match Match": [8, 160, 43], "AAProc Approx_Large - Correct": [7, 157, 63], "SAColorProc SymColor_Small - Correct": [255, 217, 17], "Add Add": [55, 143, 255], "AAColorProc ApproxColor_Large - Correct": [189, 202, 203], "SAProc Sym_Small - Correct": [98, 84, 208], "SAColorProc SymColor_Large - Correct": [232, 129, 12], "Match Cue": [96, 232, 161], "SAProc Sym_Large - Correct": [70, 121, 206], "AAProc Approx_Small - Correct": [56, 151, 51]}, "nullcondswitch": false, "jittername_input": "OpJitter", "conditionname2_input": "Procedure[Trial]", "error_input": "Num3.ACC,Num3Sym.ACC", "gapswitch": false, "experimentname_input": "<ApproxArith>", "parametricswitch": false, "onsetcolumn_input": "Num1.OnsetTime,Num1Sym.OnsetTime,AddCue.OnsetTime,ColorCue1.OnsetTime", "errorswitch": true, "jitterswitch": true, "onsettime_input": "Fixation.OnsetTime", "seperrorswitch": true, "nullswitch": false, "duration_input": "3700"}